parking_logic.v
module parking_logic (
    input wire clk,
    input wire reset,
    input wire car_entered,
    input wire is_uni_car_entered,
    input wire car_exited,
    input wire is_uni_car_exited,
    input wire [4:0] hour,
    output reg [9:0] uni_parked_car,
    output reg [9:0] parked_car,
    output reg [9:0] uni_vacated_space,
    output reg [9:0] vacated_space,
    output reg uni_is_vacated_space,
    output reg is_vacated_space
);

    parameter TOTAL_CAP = 700;
    parameter UNI_CAP = 500;
    parameter OPEN_TIME = 8;
    parameter START_INC_TIME = 13;
    parameter END_INC_TIME = 16;
    parameter INC_PER_HOUR = 50;
    parameter MAX_NON_UNI_CAP_END = 500;

    reg [9:0] non_uni_capacity;

    // Update vacated spaces and flags
    always @(*) begin
        uni_vacated_space = UNI_CAP - uni_parked_car < TOTAL_CAP - (uni_parked_car + parked_car) 
        ? UNI_CAP - uni_parked_car : TOTAL_CAP - (uni_parked_car + parked_car);
        vacated_space = non_uni_capacity - parked_car < TOTAL_CAP - (uni_parked_car + parked_car) 
        ? non_uni_capacity - parked_car : TOTAL_CAP - (uni_parked_car + parked_car);
        uni_is_vacated_space = (uni_vacated_space > 0);
        is_vacated_space = (vacated_space > 0);
    end

    // Parking logic for entering and exiting cars
    always @(posedge clk or negedge reset) begin
        if (reset) begin
            non_uni_capacity <= TOTAL_CAP - UNI_CAP;
            uni_parked_car <= 0;
            parked_car <= 0;
        end else begin
            updateNonEmployeeCapacity();
            processCarEntered();
            processCarExited();
        end
    end

    // Update non-employee capacity based on the hour
    task updateNonEmployeeCapacity();
        if (hour >= OPEN_TIME && hour < START_INC_TIME) begin
            non_uni_capacity <= TOTAL_CAP - UNI_CAP;
        end else if (hour >= START_INC_TIME && hour < END_INC_TIME) begin
            non_uni_capacity <= TOTAL_CAP - UNI_CAP + (hour - START_INC_TIME) * INC_PER_HOUR;
        end else if (hour >= END_INC_TIME) begin
            non_uni_capacity <= MAX_NON_UNI_CAP_END;
        end
    endtask

    // Process car entered events
    task processCarEntered();
        if (car_entered) begin
            if (uni_parked_car + parked_car >= TOTAL_CAP) begin
                $display("Parking lot is full. Car cannot be parked.");
            end else if (is_uni_car_entered && uni_parked_car < UNI_CAP) begin
                uni_parked_car <= uni_parked_car + 1;
            end else if (!is_uni_car_entered && parked_car < non_uni_capacity) begin
                parked_car <= parked_car + 1;
            end
        end
    endtask

    // Process car exited events
    task processCarExited();
        if (car_exited) begin
            if (is_uni_car_exited && uni_parked_car > 0) begin
                uni_parked_car <= uni_parked_car - 1;
            end else if (!is_uni_car_exited && parked_car > 0) begin
                parked_car <= parked_car - 1;
            end
        end
    endtask

endmodule

university_parking_tb.v
module university_parking_tb;

parameter CLK_PERIOD = 10; // Clock period in nanoseconds
parameter SIM_END_TIME = 10000; // Simulation end time in nanoseconds

reg clk;
reg reset;
reg car_entered;
reg is_uni_car_entered;
reg car_exited;
reg is_uni_car_exited;
reg [4:0] hour;

wire [9:0] uni_parked_car;
wire [9:0] parked_car;
wire [9:0] uni_vacated_space;
wire [9:0] vacated_space;
wire uni_is_vacated_space;
wire is_vacated_space;

parking_logic pl (
    .clk(clk),
    .reset(reset),
    .car_entered(car_entered),
    .is_uni_car_entered(is_uni_car_entered),
    .car_exited(car_exited),
    .is_uni_car_exited(is_uni_car_exited),
    .hour(hour),
    .uni_parked_car(uni_parked_car),
    .parked_car(parked_car),
    .uni_vacated_space(uni_vacated_space),
    .vacated_space(vacated_space),
    .uni_is_vacated_space(uni_is_vacated_space),
    .is_vacated_space(is_vacated_space)
);

initial clk = 0;
always #(CLK_PERIOD / 2) clk = ~clk;

task reset_sequence;
begin
    reset = 1;
    #(2 * CLK_PERIOD) reset = 0;
end
endtask

task simulate_car_activity(input integer uni_enter, uni_exit, non_uni_enter, non_uni_exit);
integer i;
begin
    for (i = 0; i < uni_enter; i++) begin
        #(CLK_PERIOD) car_entered = 1; is_uni_car_entered = 1; #(CLK_PERIOD) car_entered = 0;
    end
    for (i = 0; i < non_uni_enter; i++) begin
        #(CLK_PERIOD) car_entered = 1; is_uni_car_entered = 0; #(CLK_PERIOD) car_entered = 0;
    end
    for (i = 0; i < uni_exit; i++) begin
        #(CLK_PERIOD) car_exited = 1; is_uni_car_exited = 1; #(CLK_PERIOD) car_exited = 0;
    end
    for (i = 0; i < non_uni_exit; i++) begin
        #(CLK_PERIOD) car_exited = 1; is_uni_car_exited = 0; #(CLK_PERIOD) car_exited = 0;
    end
end
endtask

initial begin
    $monitor("Hour: %d, uni_parked_car: %d, parked_car: %d, uni_vacated_space: %d, vacated_space: %d, uni_is_vacated_space: %b, is_vacated_space: %b", 
        hour, uni_parked_car, parked_car, uni_vacated_space, vacated_space, uni_is_vacated_space, is_vacated_space);
    $dumpfile("university_parking_tb.vcd");
    $dumpvars(0, university_parking_tb);

    reset_sequence();
    hour = 8; simulate_car_activity(500, 0, 200, 100);
    hour = 14; simulate_car_activity(0, 100, 100, 0);
    hour = 15; simulate_car_activity(0, 100, 200, 0);
    hour = 16; simulate_car_activity(50, 0, 50, 0);

    #(SIM_END_TIME) $stop;
end

endmodule

university_parking_tb.vcd
$date
	Fri Jun 28 10:19:53 2024
$end
$version
	ModelSim Version 10.1d
$end
$timescale
	1ps
$end
$scope module university_parking_tb $end
$var parameter 32 ! CLK_PERIOD $end
$var parameter 32 " SIM_END_TIME $end
$var reg 1 # clk $end
$var reg 1 $ reset $end
$var reg 1 % car_entered $end
$var reg 1 & is_uni_car_entered $end
$var reg 1 ' car_exited $end
$var reg 1 ( is_uni_car_exited $end
$var reg 5 ) hour [4:0] $end
$var wire 1 * uni_parked_car [9] $end
$var wire 1 + uni_parked_car [8] $end
$var wire 1 , uni_parked_car [7] $end
$var wire 1 - uni_parked_car [6] $end
$var wire 1 . uni_parked_car [5] $end
$var wire 1 / uni_parked_car [4] $end
$var wire 1 0 uni_parked_car [3] $end
$var wire 1 1 uni_parked_car [2] $end
$var wire 1 2 uni_parked_car [1] $end
$var wire 1 3 uni_parked_car [0] $end
$var wire 1 4 parked_car [9] $end
$var wire 1 5 parked_car [8] $end
$var wire 1 6 parked_car [7] $end
$var wire 1 7 parked_car [6] $end
$var wire 1 8 parked_car [5] $end
$var wire 1 9 parked_car [4] $end
$var wire 1 : parked_car [3] $end
$var wire 1 ; parked_car [2] $end
$var wire 1 < parked_car [1] $end
$var wire 1 = parked_car [0] $end
$var wire 1 > uni_vacated_space [9] $end
$var wire 1 ? uni_vacated_space [8] $end
$var wire 1 @ uni_vacated_space [7] $end
$var wire 1 A uni_vacated_space [6] $end
$var wire 1 B uni_vacated_space [5] $end
$var wire 1 C uni_vacated_space [4] $end
$var wire 1 D uni_vacated_space [3] $end
$var wire 1 E uni_vacated_space [2] $end
$var wire 1 F uni_vacated_space [1] $end
$var wire 1 G uni_vacated_space [0] $end
$var wire 1 H vacated_space [9] $end
$var wire 1 I vacated_space [8] $end
$var wire 1 J vacated_space [7] $end
$var wire 1 K vacated_space [6] $end
$var wire 1 L vacated_space [5] $end
$var wire 1 M vacated_space [4] $end
$var wire 1 N vacated_space [3] $end
$var wire 1 O vacated_space [2] $end
$var wire 1 P vacated_space [1] $end
$var wire 1 Q vacated_space [0] $end
$var wire 1 R uni_is_vacated_space $end
$var wire 1 S is_vacated_space $end
$scope task reset_sequence $end
$upscope $end
$scope task simulate_car_activity $end
$var integer 32 T uni_enter $end
$var integer 32 U uni_exit $end
$var integer 32 V non_uni_enter $end
$var integer 32 W non_uni_exit $end
$var integer 32 X i $end
$upscope $end
$scope module pl $end
$var parameter 32 Y TOTAL_CAP $end
$var parameter 32 Z UNI_CAP $end
$var parameter 32 [ OPEN_TIME $end
$var parameter 32 \ START_INC_TIME $end
$var parameter 32 ] END_INC_TIME $end
$var parameter 32 ^ INC_PER_HOUR $end
$var parameter 32 _ MAX_NON_UNI_CAP_END $end
$var wire 1 ` clk $end
$var wire 1 a reset $end
$var wire 1 b car_entered $end
$var wire 1 c is_uni_car_entered $end
$var wire 1 d car_exited $end
$var wire 1 e is_uni_car_exited $end
$var wire 1 f hour [4] $end
$var wire 1 g hour [3] $end
$var wire 1 h hour [2] $end
$var wire 1 i hour [1] $end
$var wire 1 j hour [0] $end
$var reg 10 k uni_parked_car [9:0] $end
$var reg 10 l parked_car [9:0] $end
$var reg 10 m uni_vacated_space [9:0] $end
$var reg 10 n vacated_space [9:0] $end
$var reg 1 o uni_is_vacated_space $end
$var reg 1 p is_vacated_space $end
$var reg 10 q non_uni_capacity [9:0] $end
$scope task updateNonEmployeeCapacity $end
$upscope $end
$scope task processCarEntered $end
$upscope $end
$scope task processCarExited $end
$upscope $end
$upscope $end
$upscope $end
$enddefinitions $end
#0
$dumpvars
0#
1$
x%
x&
x'
x(
bx )
bx k
bx l
bx m
bx n
xo
xp
bx q
b1010 !
b10011100010000 "
b1010111100 Y
b111110100 Z
b1000 [
b1101 \
b10000 ]
b110010 ^
b111110100 _
bx T
bx U
bx V
bx W
bx X
x3
x2
x1
x0
x/
x.
x-
x,
x+
x*
x=
x<
x;
x:
x9
x8
x7
x6
x5
x4
xG
xF
xE
xD
xC
xB
xA
x@
x?
x>
xQ
xP
xO
xN
xM
xL
xK
xJ
xI
xH
xR
xS
0`
1a
xb
xc
xd
xe
xj
xi
xh
xg
xf
$end
#5
1#
1`
b11001000 q
b0 k
b0 l
0=
0<
0;
0:
09
08
07
06
05
04
03
02
01
00
0/
0.
0-
0,
0+
0*
b111110100 m
b11001000 n
1o
1p
0Q
0P
0O
1N
0M
0L
1K
1J
0I
0H
0G
0F
1E
0D
1C
1B
1A
1@
1?
0>
1R
1S
#10
0#
0`
#15
1#
1`
#20
0$
b1000 )
b111110100 T
b0 U
b11001000 V
b1100100 W
b0 X
0#
0j
0i
0h
1g
0f
0a
0`
#25
1#
1`
#30
1%
1&
0#
1b
1c
0`
#35
1#
1`
b1 k
13
b111110011 m
1G
1F
0E
#40
0%
b1 X
0#
0b
0`
#45
1#
1`
#50
1%
0#
1b
0`
#55
1#
1`
b10 k
03
12
b111110010 m
0G
#60
0%
b10 X
0#
0b
0`
#65
1#
1`
#70
1%
0#
1b
0`
#75
1#
1`
b11 k
13
b111110001 m
1G
0F
#80
0%
b11 X
0#
0b
0`
#85
1#
1`
#90
1%
0#
1b
0`
#95
1#
1`
b100 k
03
02
11
b111110000 m
0G
#100
0%
b100 X
0#
0b
0`
#105
1#
1`
#110
1%
0#
1b
0`
#115
1#
1`
b101 k
13
b111101111 m
1G
1F
1E
1D
0C
#120
0%
b101 X
0#
0b
0`
#125
1#
1`
#130
1%
0#
1b
0`
#135
1#
1`
b110 k
03
12
b111101110 m
0G
#140
0%
b110 X
0#
0b
0`
#145
1#
1`
#150
1%
0#
1b
0`
#155
1#
1`
b111 k
13
b111101101 m
1G
0F
#160
0%
b111 X
0#
0b
0`
#165
1#
1`
#170
1%
0#
1b
0`
#175
1#
1`
b1000 k
03
02
01
10
b111101100 m
0G
#180
0%
b1000 X
0#
0b
0`
#185
1#
1`
#190
1%
0#
1b
0`
#195
1#
1`
b1001 k
13
b111101011 m
1G
1F
0E
#200
0%
b1001 X
0#
0b
0`
#205
1#
1`
#210
1%
0#
1b
0`
#215
1#
1`
b1010 k
03
12
b111101010 m
0G
#220
0%
b1010 X
0#
0b
0`
#225
1#
1`
#230
1%
0#
1b
0`
#235
1#
1`
b1011 k
13
b111101001 m
1G
0F
#240
0%
b1011 X
0#
0b
0`
#245
1#
1`
#250
1%
0#
1b
0`
#255
1#
1`
b1100 k
03
02
11
b111101000 m
0G
#260
0%
b1100 X
0#
0b
0`
#265
1#
1`
#270
1%
0#
1b
0`
#275
1#
1`
b1101 k
13
b111100111 m
1G
1F
1E
0D
#280
0%
b1101 X
0#
0b
0`
#285
1#
1`
#290
1%
0#
1b
0`
#295
1#
1`
b1110 k
03
12
b111100110 m
0G
#300
0%
b1110 X
0#
0b
0`
#305
1#
1`
#310
1%
0#
1b
0`
#315
1#
1`
b1111 k
13
b111100101 m
1G
0F
#320
0%
b1111 X
0#
0b
0`
#325
1#
1`
#330
1%
0#
1b
0`
#335
1#
1`
b10000 k
03
02
01
00
1/
b111100100 m
0G
#340
0%
b10000 X
0#
0b
0`
#345
1#
1`
#350
1%
0#
1b
0`
#355
1#
1`
b10001 k
13
b111100011 m
1G
1F
0E
#360
0%
b10001 X
0#
0b
0`
#365
1#
1`
#370
1%
0#
1b
0`
#375
1#
1`
b10010 k
03
12
b111100010 m
0G
#380
0%
b10010 X
0#
0b
0`
#385
1#
1`
#390
1%
0#
1b
0`
#395
1#
1`
b10011 k
13
b111100001 m
1G
0F
#400
0%
b10011 X
0#
0b
0`
#405
1#
1`
#410
1%
0#
1b
0`
#415
1#
1`
b10100 k
03
02
11
b111100000 m
0G
#420
0%
b10100 X
0#
0b
0`
#425
1#
1`
#430
1%
0#
1b
0`
#435
1#
1`
b10101 k
13
b111011111 m
1G
1F
1E
1D
1C
0B
#440
0%
b10101 X
0#
0b
0`
#445
1#
1`
#450
1%
0#
1b
0`
#455
1#
1`
b10110 k
03
12
b111011110 m
0G
#460
0%
b10110 X
0#
0b
0`
#465
1#
1`
#470
1%
0#
1b
0`
#475
1#
1`
b10111 k
13
b111011101 m
1G
0F
#480
0%
b10111 X
0#
0b
0`
#485
1#
1`
#490
1%
0#
1b
0`
#495
1#
1`
b11000 k
03
02
01
10
b111011100 m
0G
#500
0%
b11000 X
0#
0b
0`
#505
1#
1`
#510
1%
0#
1b
0`
#515
1#
1`
b11001 k
13
b111011011 m
1G
1F
0E
#520
0%
b11001 X
0#
0b
0`
#525
1#
1`
#530
1%
0#
1b
0`
#535
1#
1`
b11010 k
03
12
b111011010 m
0G
#540
0%
b11010 X
0#
0b
0`
#545
1#
1`
#550
1%
0#
1b
0`
#555
1#
1`
b11011 k
13
b111011001 m
1G
0F
#560
0%
b11011 X
0#
0b
0`
#565
1#
1`
#570
1%
0#
1b
0`
#575
1#
1`
b11100 k
03
02
11
b111011000 m
0G
#580
0%
b11100 X
0#
0b
0`
#585
1#
1`
#590
1%
0#
1b
0`
#595
1#
1`
b11101 k
13
b111010111 m
1G
1F
1E
0D
#600
0%
b11101 X
0#
0b
0`
#605
1#
1`
#610
1%
0#
1b
0`
#615
1#
1`
b11110 k
03
12
b111010110 m
0G
#620
0%
b11110 X
0#
0b
0`
#625
1#
1`
#630
1%
0#
1b
0`
#635
1#
1`
b11111 k
13
b111010101 m
1G
0F
#640
0%
b11111 X
0#
0b
0`
#645
1#
1`
#650
1%
0#
1b
0`
#655
1#
1`
b100000 k
03
02
01
00
0/
1.
b111010100 m
0G
#660
0%
b100000 X
0#
0b
0`
#665
1#
1`
#670
1%
0#
1b
0`
#675
1#
1`
b100001 k
13
b111010011 m
1G
1F
0E
#680
0%
b100001 X
0#
0b
0`
#685
1#
1`
#690
1%
0#
1b
0`
#695
1#
1`
b100010 k
03
12
b111010010 m
0G
#700
0%
b100010 X
0#
0b
0`
#705
1#
1`
#710
1%
0#
1b
0`
#715
1#
1`
b100011 k
13
b111010001 m
1G
0F
#720
0%
b100011 X
0#
0b
0`
#725
1#
1`
#730
1%
0#
1b
0`
#735
1#
1`
b100100 k
03
02
11
b111010000 m
0G
#740
0%
b100100 X
0#
0b
0`
#745
1#
1`
#750
1%
0#
1b
0`
#755
1#
1`
b100101 k
13
b111001111 m
1G
1F
1E
1D
0C
#760
0%
b100101 X
0#
0b
0`
#765
1#
1`
#770
1%
0#
1b
0`
#775
1#
1`
b100110 k
03
12
b111001110 m
0G
#780
0%
b100110 X
0#
0b
0`
#785
1#
1`
#790
1%
0#
1b
0`
#795
1#
1`
b100111 k
13
b111001101 m
1G
0F
#800
0%
b100111 X
0#
0b
0`
#805
1#
1`
#810
1%
0#
1b
0`
#815
1#
1`
b101000 k
03
02
01
10
b111001100 m
0G
#820
0%
b101000 X
0#
0b
0`
#825
1#
1`
#830
1%
0#
1b
0`
#835
1#
1`
b101001 k
13
b111001011 m
1G
1F
0E
#840
0%
b101001 X
0#
0b
0`
#845
1#
1`
#850
1%
0#
1b
0`
#855
1#
1`
b101010 k
03
12
b111001010 m
0G
#860
0%
b101010 X
0#
0b
0`
#865
1#
1`
#870
1%
0#
1b
0`
#875
1#
1`
b101011 k
13
b111001001 m
1G
0F
#880
0%
b101011 X
0#
0b
0`
#885
1#
1`
#890
1%
0#
1b
0`
#895
1#
1`
b101100 k
03
02
11
b111001000 m
0G
#900
0%
b101100 X
0#
0b
0`
#905
1#
1`
#910
1%
0#
1b
0`
#915
1#
1`
b101101 k
13
b111000111 m
1G
1F
1E
0D
#920
0%
b101101 X
0#
0b
0`
#925
1#
1`
#930
1%
0#
1b
0`
#935
1#
1`
b101110 k
03
12
b111000110 m
0G
#940
0%
b101110 X
0#
0b
0`
#945
1#
1`
#950
1%
0#
1b
0`
#955
1#
1`
b101111 k
13
b111000101 m
1G
0F
#960
0%
b101111 X
0#
0b
0`
#965
1#
1`
#970
1%
0#
1b
0`
#975
1#
1`
b110000 k
03
02
01
00
1/
b111000100 m
0G
#980
0%
b110000 X
0#
0b
0`
#985
1#
1`
#990
1%
0#
1b
0`
#995
1#
1`
b110001 k
13
b111000011 m
1G
1F
0E
#1000
0%
b110001 X
0#
0b
0`
#1005
1#
1`
#1010
1%
0#
1b
0`
#1015
1#
1`
b110010 k
03
12
b111000010 m
0G
#1020
0%
b110010 X
0#
0b
0`
#1025
1#
1`
#1030
1%
0#
1b
0`
#1035
1#
1`
b110011 k
13
b111000001 m
1G
0F
#1040
0%
b110011 X
0#
0b
0`
#1045
1#
1`
#1050
1%
0#
1b
0`
#1055
1#
1`
b110100 k
03
02
11
b111000000 m
0G
#1060
0%
b110100 X
0#
0b
0`
#1065
1#
1`
#1070
1%
0#
1b
0`
#1075
1#
1`
b110101 k
13
b110111111 m
1G
1F
1E
1D
1C
1B
0A
#1080
0%
b110101 X
0#
0b
0`
#1085
1#
1`
#1090
1%
0#
1b
0`
#1095
1#
1`
b110110 k
03
12
b110111110 m
0G
#1100
0%
b110110 X
0#
0b
0`
#1105
1#
1`
#1110
1%
0#
1b
0`
#1115
1#
1`
b110111 k
13
b110111101 m
1G
0F
#1120
0%
b110111 X
0#
0b
0`
#1125
1#
1`
#1130
1%
0#
1b
0`
#1135
1#
1`
b111000 k
03
02
01
10
b110111100 m
0G
#1140
0%
b111000 X
0#
0b
0`
#1145
1#
1`
#1150
1%
0#
1b
0`
#1155
1#
1`
b111001 k
13
b110111011 m
1G
1F
0E
#1160
0%
b111001 X
0#
0b
0`
#1165
1#
1`
#1170
1%
0#
1b
0`
#1175
1#
1`
b111010 k
03
12
b110111010 m
0G
#1180
0%
b111010 X
0#
0b
0`
#1185
1#
1`
#1190
1%
0#
1b
0`
#1195
1#
1`
b111011 k
13
b110111001 m
1G
0F
#1200
0%
b111011 X
0#
0b
0`
#1205
1#
1`
#1210
1%
0#
1b
0`
#1215
1#
1`
b111100 k
03
02
11
b110111000 m
0G
#1220
0%
b111100 X
0#
0b
0`
#1225
1#
1`
#1230
1%
0#
1b
0`
#1235
1#
1`
b111101 k
13
b110110111 m
1G
1F
1E
0D
#1240
0%
b111101 X
0#
0b
0`
#1245
1#
1`
#1250
1%
0#
1b
0`
#1255
1#
1`
b111110 k
03
12
b110110110 m
0G
#1260
0%
b111110 X
0#
0b
0`
#1265
1#
1`
#1270
1%
0#
1b
0`
#1275
1#
1`
b111111 k
13
b110110101 m
1G
0F
#1280
0%
b111111 X
0#
0b
0`
#1285
1#
1`
#1290
1%
0#
1b
0`
#1295
1#
1`
b1000000 k
03
02
01
00
0/
0.
1-
b110110100 m
0G
#1300
0%
b1000000 X
0#
0b
0`
#1305
1#
1`
#1310
1%
0#
1b
0`
#1315
1#
1`
b1000001 k
13
b110110011 m
1G
1F
0E
#1320
0%
b1000001 X
0#
0b
0`
#1325
1#
1`
#1330
1%
0#
1b
0`
#1335
1#
1`
b1000010 k
03
12
b110110010 m
0G
#1340
0%
b1000010 X
0#
0b
0`
#1345
1#
1`
#1350
1%
0#
1b
0`
#1355
1#
1`
b1000011 k
13
b110110001 m
1G
0F
#1360
0%
b1000011 X
0#
0b
0`
#1365
1#
1`
#1370
1%
0#
1b
0`
#1375
1#
1`
b1000100 k
03
02
11
b110110000 m
0G
#1380
0%
b1000100 X
0#
0b
0`
#1385
1#
1`
#1390
1%
0#
1b
0`
#1395
1#
1`
b1000101 k
13
b110101111 m
1G
1F
1E
1D
0C
#1400
0%
b1000101 X
0#
0b
0`
#1405
1#
1`
#1410
1%
0#
1b
0`
#1415
1#
1`
b1000110 k
03
12
b110101110 m
0G
#1420
0%
b1000110 X
0#
0b
0`
#1425
1#
1`
#1430
1%
0#
1b
0`
#1435
1#
1`
b1000111 k
13
b110101101 m
1G
0F
#1440
0%
b1000111 X
0#
0b
0`
#1445
1#
1`
#1450
1%
0#
1b
0`
#1455
1#
1`
b1001000 k
03
02
01
10
b110101100 m
0G
#1460
0%
b1001000 X
0#
0b
0`
#1465
1#
1`
#1470
1%
0#
1b
0`
#1475
1#
1`
b1001001 k
13
b110101011 m
1G
1F
0E
#1480
0%
b1001001 X
0#
0b
0`
#1485
1#
1`
#1490
1%
0#
1b
0`
#1495
1#
1`
b1001010 k
03
12
b110101010 m
0G
#1500
0%
b1001010 X
0#
0b
0`
#1505
1#
1`
#1510
1%
0#
1b
0`
#1515
1#
1`
b1001011 k
13
b110101001 m
1G
0F
#1520
0%
b1001011 X
0#
0b
0`
#1525
1#
1`
#1530
1%
0#
1b
0`
#1535
1#
1`
b1001100 k
03
02
11
b110101000 m
0G
#1540
0%
b1001100 X
0#
0b
0`
#1545
1#
1`
#1550
1%
0#
1b
0`
#1555
1#
1`
b1001101 k
13
b110100111 m
1G
1F
1E
0D
#1560
0%
b1001101 X
0#
0b
0`
#1565
1#
1`
#1570
1%
0#
1b
0`
#1575
1#
1`
b1001110 k
03
12
b110100110 m
0G
#1580
0%
b1001110 X
0#
0b
0`
#1585
1#
1`
#1590
1%
0#
1b
0`
#1595
1#
1`
b1001111 k
13
b110100101 m
1G
0F
#1600
0%
b1001111 X
0#
0b
0`
#1605
1#
1`
#1610
1%
0#
1b
0`
#1615
1#
1`
b1010000 k
03
02
01
00
1/
b110100100 m
0G
#1620
0%
b1010000 X
0#
0b
0`
#1625
1#
1`
#1630
1%
0#
1b
0`
#1635
1#
1`
b1010001 k
13
b110100011 m
1G
1F
0E
#1640
0%
b1010001 X
0#
0b
0`
#1645
1#
1`
#1650
1%
0#
1b
0`
#1655
1#
1`
b1010010 k
03
12
b110100010 m
0G
#1660
0%
b1010010 X
0#
0b
0`
#1665
1#
1`
#1670
1%
0#
1b
0`
#1675
1#
1`
b1010011 k
13
b110100001 m
1G
0F
#1680
0%
b1010011 X
0#
0b
0`
#1685
1#
1`
#1690
1%
0#
1b
0`
#1695
1#
1`
b1010100 k
03
02
11
b110100000 m
0G
#1700
0%
b1010100 X
0#
0b
0`
#1705
1#
1`
#1710
1%
0#
1b
0`
#1715
1#
1`
b1010101 k
13
b110011111 m
1G
1F
1E
1D
1C
0B
#1720
0%
b1010101 X
0#
0b
0`
#1725
1#
1`
#1730
1%
0#
1b
0`
#1735
1#
1`
b1010110 k
03
12
b110011110 m
0G
#1740
0%
b1010110 X
0#
0b
0`
#1745
1#
1`
#1750
1%
0#
1b
0`
#1755
1#
1`
b1010111 k
13
b110011101 m
1G
0F
#1760
0%
b1010111 X
0#
0b
0`
#1765
1#
1`
#1770
1%
0#
1b
0`
#1775
1#
1`
b1011000 k
03
02
01
10
b110011100 m
0G
#1780
0%
b1011000 X
0#
0b
0`
#1785
1#
1`
#1790
1%
0#
1b
0`
#1795
1#
1`
b1011001 k
13
b110011011 m
1G
1F
0E
#1800
0%
b1011001 X
0#
0b
0`
#1805
1#
1`
#1810
1%
0#
1b
0`
#1815
1#
1`
b1011010 k
03
12
b110011010 m
0G
#1820
0%
b1011010 X
0#
0b
0`
#1825
1#
1`
#1830
1%
0#
1b
0`
#1835
1#
1`
b1011011 k
13
b110011001 m
1G
0F
#1840
0%
b1011011 X
0#
0b
0`
#1845
1#
1`
#1850
1%
0#
1b
0`
#1855
1#
1`
b1011100 k
03
02
11
b110011000 m
0G
#1860
0%
b1011100 X
0#
0b
0`
#1865
1#
1`
#1870
1%
0#
1b
0`
#1875
1#
1`
b1011101 k
13
b110010111 m
1G
1F
1E
0D
#1880
0%
b1011101 X
0#
0b
0`
#1885
1#
1`
#1890
1%
0#
1b
0`
#1895
1#
1`
b1011110 k
03
12
b110010110 m
0G
#1900
0%
b1011110 X
0#
0b
0`
#1905
1#
1`
#1910
1%
0#
1b
0`
#1915
1#
1`
b1011111 k
13
b110010101 m
1G
0F
#1920
0%
b1011111 X
0#
0b
0`
#1925
1#
1`
#1930
1%
0#
1b
0`
#1935
1#
1`
b1100000 k
03
02
01
00
0/
1.
b110010100 m
0G
#1940
0%
b1100000 X
0#
0b
0`
#1945
1#
1`
#1950
1%
0#
1b
0`
#1955
1#
1`
b1100001 k
13
b110010011 m
1G
1F
0E
#1960
0%
b1100001 X
0#
0b
0`
#1965
1#
1`
#1970
1%
0#
1b
0`
#1975
1#
1`
b1100010 k
03
12
b110010010 m
0G
#1980
0%
b1100010 X
0#
0b
0`
#1985
1#
1`
#1990
1%
0#
1b
0`
#1995
1#
1`
b1100011 k
13
b110010001 m
1G
0F
#2000
0%
b1100011 X
0#
0b
0`
#2005
1#
1`
#2010
1%
0#
1b
0`
#2015
1#
1`
b1100100 k
03
02
11
b110010000 m
0G
#2020
0%
b1100100 X
0#
0b
0`
#2025
1#
1`
#2030
1%
0#
1b
0`
#2035
1#
1`
b1100101 k
13
b110001111 m
1G
1F
1E
1D
0C
#2040
0%
b1100101 X
0#
0b
0`
#2045
1#
1`
#2050
1%
0#
1b
0`
#2055
1#
1`
b1100110 k
03
12
b110001110 m
0G
#2060
0%
b1100110 X
0#
0b
0`
#2065
1#
1`
#2070
1%
0#
1b
0`
#2075
1#
1`
b1100111 k
13
b110001101 m
1G
0F
#2080
0%
b1100111 X
0#
0b
0`
#2085
1#
1`
#2090
1%
0#
1b
0`
#2095
1#
1`
b1101000 k
03
02
01
10
b110001100 m
0G
#2100
0%
b1101000 X
0#
0b
0`
#2105
1#
1`
#2110
1%
0#
1b
0`
#2115
1#
1`
b1101001 k
13
b110001011 m
1G
1F
0E
#2120
0%
b1101001 X
0#
0b
0`
#2125
1#
1`
#2130
1%
0#
1b
0`
#2135
1#
1`
b1101010 k
03
12
b110001010 m
0G
#2140
0%
b1101010 X
0#
0b
0`
#2145
1#
1`
#2150
1%
0#
1b
0`
#2155
1#
1`
b1101011 k
13
b110001001 m
1G
0F
#2160
0%
b1101011 X
0#
0b
0`
#2165
1#
1`
#2170
1%
0#
1b
0`
#2175
1#
1`
b1101100 k
03
02
11
b110001000 m
0G
#2180
0%
b1101100 X
0#
0b
0`
#2185
1#
1`
#2190
1%
0#
1b
0`
#2195
1#
1`
b1101101 k
13
b110000111 m
1G
1F
1E
0D
#2200
0%
b1101101 X
0#
0b
0`
#2205
1#
1`
#2210
1%
0#
1b
0`
#2215
1#
1`
b1101110 k
03
12
b110000110 m
0G
#2220
0%
b1101110 X
0#
0b
0`
#2225
1#
1`
#2230
1%
0#
1b
0`
#2235
1#
1`
b1101111 k
13
b110000101 m
1G
0F
#2240
0%
b1101111 X
0#
0b
0`
#2245
1#
1`
#2250
1%
0#
1b
0`
#2255
1#
1`
b1110000 k
03
02
01
00
1/
b110000100 m
0G
#2260
0%
b1110000 X
0#
0b
0`
#2265
1#
1`
#2270
1%
0#
1b
0`
#2275
1#
1`
b1110001 k
13
b110000011 m
1G
1F
0E
#2280
0%
b1110001 X
0#
0b
0`
#2285
1#
1`
#2290
1%
0#
1b
0`
#2295
1#
1`
b1110010 k
03
12
b110000010 m
0G
#2300
0%
b1110010 X
0#
0b
0`
#2305
1#
1`
#2310
1%
0#
1b
0`
#2315
1#
1`
b1110011 k
13
b110000001 m
1G
0F
#2320
0%
b1110011 X
0#
0b
0`
#2325
1#
1`
#2330
1%
0#
1b
0`
#2335
1#
1`
b1110100 k
03
02
11
b110000000 m
0G
#2340
0%
b1110100 X
0#
0b
0`
#2345
1#
1`
#2350
1%
0#
1b
0`
#2355
1#
1`
b1110101 k
13
b101111111 m
1G
1F
1E
1D
1C
1B
1A
0@
#2360
0%
b1110101 X
0#
0b
0`
#2365
1#
1`
#2370
1%
0#
1b
0`
#2375
1#
1`
b1110110 k
03
12
b101111110 m
0G
#2380
0%
b1110110 X
0#
0b
0`
#2385
1#
1`
#2390
1%
0#
1b
0`
#2395
1#
1`
b1110111 k
13
b101111101 m
1G
0F
#2400
0%
b1110111 X
0#
0b
0`
#2405
1#
1`
#2410
1%
0#
1b
0`
#2415
1#
1`
b1111000 k
03
02
01
10
b101111100 m
0G
#2420
0%
b1111000 X
0#
0b
0`
#2425
1#
1`
#2430
1%
0#
1b
0`
#2435
1#
1`
b1111001 k
13
b101111011 m
1G
1F
0E
#2440
0%
b1111001 X
0#
0b
0`
#2445
1#
1`
#2450
1%
0#
1b
0`
#2455
1#
1`
b1111010 k
03
12
b101111010 m
0G
#2460
0%
b1111010 X
0#
0b
0`
#2465
1#
1`
#2470
1%
0#
1b
0`
#2475
1#
1`
b1111011 k
13
b101111001 m
1G
0F
#2480
0%
b1111011 X
0#
0b
0`
#2485
1#
1`
#2490
1%
0#
1b
0`
#2495
1#
1`
b1111100 k
03
02
11
b101111000 m
0G
#2500
0%
b1111100 X
0#
0b
0`
#2505
1#
1`
#2510
1%
0#
1b
0`
#2515
1#
1`
b1111101 k
13
b101110111 m
1G
1F
1E
0D
#2520
0%
b1111101 X
0#
0b
0`
#2525
1#
1`
#2530
1%
0#
1b
0`
